PytTorus/__init__.py
PytTorus/_torus.cpython-310-darwin.so
PytTorus-0.0.4.dist-info/METADATA
PytTorus-0.0.4.dist-info/WHEEL
PytTorus-0.0.4.dist-info/top_level.txt
PytTorus-0.0.4.dist-info/RECORD
