Metadata-Version: 2.1
Name: PytTorus
Version: 0.0.4
Summary: Torus library for orbital mechanics and galactic dynamics modeling
Author: Sean Ly
Author-email: Sean Ly <seanly1101@gmail.com>
License: MIT
Project-URL: Homepage, https://github.com/seanly/PytTorus
Project-URL: Documentation, https://pytorus.readthedocs.io
Project-URL: Source, https://github.com/seanly/PytTorus
Requires-Python: >=3.7
Requires-Dist: pybind11
